setup.py
zillogaussdist/Binomialdistribution.py
zillogaussdist/Gaussiandistribution.py
zillogaussdist/Generaldistribution.py
zillogaussdist/__init__.py
zillogaussdist.egg-info/PKG-INFO
zillogaussdist.egg-info/SOURCES.txt
zillogaussdist.egg-info/dependency_links.txt
zillogaussdist.egg-info/not-zip-safe
zillogaussdist.egg-info/top_level.txt