Metadata-Version: 1.0
Name: zillogaussdist
Version: 1.0
Summary: Gaussian distributions
Home-page: https://github.com/zillobit/
Author: Chinedu Osuh
Author-email: osuhchinedu91@gmail.com
License: UNKNOWN
Platform: UNKNOWN
